terrable/__init__.py
terrable/_definitions.py
terrable/_lister.py
terrable/_publisher.py
terrable/_s3.py
terrable/_utils.py
terrable/tests/__init__.py
terrable/tests/modules/foo/main.tf
terrable/tests/test_list.py
terrable/tests/test_list.yaml
terrable/tests/test_list_modules.yaml
terrable/tests/test_list_verbose.yaml
terrable/tests/test_publish.py
terrable/tests/test_publish.yaml
terrable/tests/test_utils_compare_zip_files/__init__.py
terrable/tests/test_utils_compare_zip_files/scenarios/different-files.yaml
terrable/tests/test_utils_compare_zip_files/scenarios/identical.yaml
terrable/tests/test_utils_compare_zip_files/scenarios/modified-file.yaml
terrable/tests/test_utils_compare_zip_files/scenarios/no-changes.yaml
terrable/tests/test_utils_compare_zip_files/sources/different-files.zip
terrable/tests/test_utils_compare_zip_files/sources/modified-file.zip
terrable/tests/test_utils_compare_zip_files/sources/original.zip
terrable/tests/test_utils_compare_zip_files/sources/unchanged.zip
terrable/tests/test_utils_compare_zip_files/test_compare_zip_files.py
terrable-0.2.1.dist-info/entry_points.txt
terrable-0.2.1.dist-info/LICENSE
terrable-0.2.1.dist-info/WHEEL
terrable-0.2.1.dist-info/METADATA
terrable-0.2.1.dist-info/RECORD
