Metadata-Version: 2.1
Name: terrable
Version: 0.2.1
Summary: Manage private shared terraform modules deployed to S3.
Home-page: https://gitlab.com/rocket-boosters/terrable
License: MIT
Keywords: terraform,s3,modules
Author: Scott Ernst
Author-email: swernst@gmail.com
Requires-Python: >=3.8,<4.0
Classifier: Development Status :: 4 - Beta
Classifier: Environment :: Console
Classifier: Intended Audience :: Developers
Classifier: License :: OSI Approved :: MIT License
Classifier: Programming Language :: Python :: 3
Classifier: Programming Language :: Python :: 3.8
Classifier: Programming Language :: Python :: 3.9
Classifier: Topic :: Utilities
Classifier: Typing :: Typed
Requires-Dist: boto3 (>=1.16.16,<2.0.0)
Project-URL: Documentation, https://gitlab.com/rocket-boosters/terrable
Project-URL: Repository, https://gitlab.com/rocket-boosters/terrable
